nbvscode.py
jupyter_vscode_server-0.0.10.dist-info/LICENSE
jupyter_vscode_server-0.0.10.dist-info/METADATA
jupyter_vscode_server-0.0.10.dist-info/WHEEL
jupyter_vscode_server-0.0.10.dist-info/entry_points.txt
jupyter_vscode_server-0.0.10.dist-info/top_level.txt
jupyter_vscode_server-0.0.10.dist-info/RECORD
