Metadata-Version: 2.1
Name: jupyter-vscode-server
Version: 0.0.10
Summary: A Jupyter extension to launch VS Code
Home-page: https://github.com/tlkh/jupyter-vscode-server
Author: Timothy Liu
Author-email: timothyl@nvidia.com
License: UNKNOWN
Platform: UNKNOWN
Classifier: Programming Language :: Python :: 3
Classifier: License :: OSI Approved :: MIT License
Classifier: Operating System :: POSIX :: Linux 
Requires-Dist: jupyter-server-proxy
